asf_tools/README.md
asf_tools/__init__.py
asf_tools/__main__.py
asf_tools/aws.py
asf_tools/composite.py
asf_tools/dem.py
asf_tools/raster.py
asf_tools/tile.py
asf_tools/util.py
asf_tools/vector.py
asf_tools/etc/entrypoint.sh
asf_tools/hydrosar/__init__.py
asf_tools/hydrosar/flood_map.py
asf_tools/hydrosar/threshold.py
asf_tools/hydrosar/water_map.py
asf_tools/hydrosar/data/water_extent.vrt
asf_tools/hydrosar/hand/__init__.py
asf_tools/hydrosar/hand/calculate.py
asf_tools/hydrosar/hand/prepare.py
asf_tools/watermasking/README.md
asf_tools/watermasking/__init__.py
asf_tools/watermasking/fill_missing_tiles.py
asf_tools/watermasking/generate_osm_tiles.py
asf_tools/watermasking/generate_worldcover_tiles.py
asf_tools/watermasking/utils.py
asf_tools-0.8.4.dist-info/licenses/LICENSE
asf_tools-0.8.4.dist-info/METADATA
asf_tools-0.8.4.dist-info/WHEEL
asf_tools-0.8.4.dist-info/entry_points.txt
asf_tools-0.8.4.dist-info/top_level.txt
asf_tools-0.8.4.dist-info/RECORD
