Metadata-Version: 2.4
Name: asf_tools
Version: 0.8.4
Summary: Tools developed by ASF for working with SAR data
Author-email: ASF APD/Tools Team <uaf-asf-apd@alaska.edu>
License: BSD-3-Clause
Project-URL: Homepage, https://github.com/ASFHyP3/asf-tools
Project-URL: Bug Tracker, https://github.com/ASFHyP3/asf-tools/issues
Classifier: Intended Audience :: Science/Research
Classifier: License :: OSI Approved :: BSD License
Classifier: Natural Language :: English
Classifier: Operating System :: OS Independent
Classifier: Programming Language :: Python :: 3
Classifier: Programming Language :: Python :: 3.10
Classifier: Programming Language :: Python :: 3.11
Requires-Python: >=3.10
License-File: LICENSE
Requires-Dist: astropy
Requires-Dist: boto3>=1.36.0
Requires-Dist: fiona
Requires-Dist: gdal>=3.3
Requires-Dist: geopandas
Requires-Dist: numpy
Requires-Dist: pyogrio
Requires-Dist: pysheds>=0.3
Requires-Dist: rasterio
Requires-Dist: scikit-fuzzy
Requires-Dist: scikit-image
Requires-Dist: scipy
Requires-Dist: shapely
Provides-Extra: develop
Requires-Dist: gdal-utils; extra == "develop"
Requires-Dist: ruff; extra == "develop"
Requires-Dist: mypy; extra == "develop"
Requires-Dist: pytest; extra == "develop"
Requires-Dist: pytest-cov; extra == "develop"
Requires-Dist: pytest-console-scripts; extra == "develop"
Dynamic: license-file
